{
    "statusCode": 200,
    "body": {
        "latitude": 53.79972,
        "longitude": -1.54917,
        "timezone": "Europe/London",
        "currently": {
            "time": 1559573019,
            "summary": "Partly Cloudy",
            "icon": "partly-cloudy-day",
            "nearestStormDistance": 83,
            "nearestStormBearing": 143,
            "precipIntensity": 0,
            "precipProbability": 0,
            "temperature": 66.98,
            "apparentTemperature": 66.98,
            "dewPoint": 37.21,
            "humidity": 0.33,
            "pressure": 1008.89,
            "windSpeed": 14.9,
            "windGust": 27.72,
            "windBearing": 252,
            "cloudCover": 0.48,
            "uvIndex": 3,
            "visibility": 6.22,
            "ozone": 384.04
        },
        "minutely": {
            "summary": "Partly cloudy for the hour.",
            "icon": "partly-cloudy-day",
            "data": [{
                "time": 1559572980,
                "precipIntensity": 0,
                "precipProbability": 0
            }, {
                "time": 1559573040,
                "precipIntensity": 0,
                "precipProbability": 0
            }, {
                "time": 1559573100,
                "precipIntensity": 0,
                "precipProbability": 0
            }, {
                "time": 1559573160,
                "precipIntensity": 0,
                "precipProbability": 0
            }, {
                "time": 1559573220,
                "precipIntensity": 0,
                "precipProbability": 0
            }, {
                "time": 1559573280,
                "precipIntensity": 0,
                "precipProbability": 0
            }, {
                "time": 1559573340,
                "precipIntensity": 0,
                "precipProbability": 0
            }, {
                "time": 1559573400,
                "precipIntensity": 0,
                "precipProbability": 0
            }, {
                "time": 1559573460,
                "precipIntensity": 0,
                "precipProbability": 0
            }, {
                "time": 1559573520,
                "precipIntensity": 0,
                "precipProbability": 0
            }, {
                "time": 1559573580,
                "precipIntensity": 0,
                "precipProbability": 0
            }, {
                "time": 1559573640,
                "precipIntensity": 0,
                "precipProbability": 0
            }, {
                "time": 1559573700,
                "precipIntensity": 0,
                "precipProbability": 0
            }, {
                "time": 1559573760,
                "precipIntensity": 0,
                "precipProbability": 0
            }, {
                "time": 1559573820,
                "precipIntensity": 0,
                "precipProbability": 0
            }, {
                "time": 1559573880,
                "precipIntensity": 0,
                "precipProbability": 0
            }, {
                "time": 1559573940,
                "precipIntensity": 0,
                "precipProbability": 0
            }, {
                "time": 1559574000,
                "precipIntensity": 0,
                "precipProbability": 0
            }, {
                "time": 1559574060,
                "precipIntensity": 0,
                "precipProbability": 0
            }, {
                "time": 1559574120,
                "precipIntensity": 0,
                "precipProbability": 0
            }, {
                "time": 1559574180,
                "precipIntensity": 0,
                "precipProbability": 0
            }, {
                "time": 1559574240,
                "precipIntensity": 0,
                "precipProbability": 0
            }, {
                "time": 1559574300,
                "precipIntensity": 0,
                "precipProbability": 0
            }, {
                "time": 1559574360,
                "precipIntensity": 0,
                "precipProbability": 0
            }, {
                "time": 1559574420,
                "precipIntensity": 0,
                "precipProbability": 0
            }, {
                "time": 1559574480,
                "precipIntensity": 0,
                "precipProbability": 0
            }, {
                "time": 1559574540,
                "precipIntensity": 0,
                "precipProbability": 0
            }, {
                "time": 1559574600,
                "precipIntensity": 0,
                "precipProbability": 0
            }, {
                "time": 1559574660,
                "precipIntensity": 0,
                "precipProbability": 0
            }, {
                "time": 1559574720,
                "precipIntensity": 0,
                "precipProbability": 0
            }, {
                "time": 1559574780,
                "precipIntensity": 0,
                "precipProbability": 0
            }, {
                "time": 1559574840,
                "precipIntensity": 0,
                "precipProbability": 0
            }, {
                "time": 1559574900,
                "precipIntensity": 0,
                "precipProbability": 0
            }, {
                "time": 1559574960,
                "precipIntensity": 0,
                "precipProbability": 0
            }, {
                "time": 1559575020,
                "precipIntensity": 0,
                "precipProbability": 0
            }, {
                "time": 1559575080,
                "precipIntensity": 0,
                "precipProbability": 0
            }, {
                "time": 1559575140,
                "precipIntensity": 0,
                "precipProbability": 0
            }, {
                "time": 1559575200,
                "precipIntensity": 0,
                "precipProbability": 0
            }, {
                "time": 1559575260,
                "precipIntensity": 0,
                "precipProbability": 0
            }, {
                "time": 1559575320,
                "precipIntensity": 0,
                "precipProbability": 0
            }, {
                "time": 1559575380,
                "precipIntensity": 0,
                "precipProbability": 0
            }, {
                "time": 1559575440,
                "precipIntensity": 0,
                "precipProbability": 0
            }, {
                "time": 1559575500,
                "precipIntensity": 0,
                "precipProbability": 0
            }, {
                "time": 1559575560,
                "precipIntensity": 0,
                "precipProbability": 0
            }, {
                "time": 1559575620,
                "precipIntensity": 0,
                "precipProbability": 0
            }, {
                "time": 1559575680,
                "precipIntensity": 0,
                "precipProbability": 0
            }, {
                "time": 1559575740,
                "precipIntensity": 0,
                "precipProbability": 0
            }, {
                "time": 1559575800,
                "precipIntensity": 0,
                "precipProbability": 0
            }, {
                "time": 1559575860,
                "precipIntensity": 0,
                "precipProbability": 0
            }, {
                "time": 1559575920,
                "precipIntensity": 0,
                "precipProbability": 0
            }, {
                "time": 1559575980,
                "precipIntensity": 0,
                "precipProbability": 0
            }, {
                "time": 1559576040,
                "precipIntensity": 0,
                "precipProbability": 0
            }, {
                "time": 1559576100,
                "precipIntensity": 0,
                "precipProbability": 0
            }, {
                "time": 1559576160,
                "precipIntensity": 0,
                "precipProbability": 0
            }, {
                "time": 1559576220,
                "precipIntensity": 0,
                "precipProbability": 0
            }, {
                "time": 1559576280,
                "precipIntensity": 0,
                "precipProbability": 0
            }, {
                "time": 1559576340,
                "precipIntensity": 0,
                "precipProbability": 0
            }, {
                "time": 1559576400,
                "precipIntensity": 0,
                "precipProbability": 0
            }, {
                "time": 1559576460,
                "precipIntensity": 0,
                "precipProbability": 0
            }, {
                "time": 1559576520,
                "precipIntensity": 0,
                "precipProbability": 0
            }, {
                "time": 1559576580,
                "precipIntensity": 0,
                "precipProbability": 0
            }]
        },
        "hourly": {
            "summary": "Mostly cloudy starting tomorrow morning.",
            "icon": "partly-cloudy-day",
            "data": [{
                "time": 1559570400,
                "summary": "Partly Cloudy",
                "icon": "partly-cloudy-day",
                "precipIntensity": 0,
                "precipProbability": 0,
                "temperature": 66.19,
                "apparentTemperature": 66.19,
                "dewPoint": 37.48,
                "humidity": 0.35,
                "pressure": 1008.86,
                "windSpeed": 15.19,
                "windGust": 28.31,
                "windBearing": 250,
                "cloudCover": 0.44,
                "uvIndex": 4,
                "visibility": 6.22,
                "ozone": 384.33
            }, {
                "time": 1559574000,
                "summary": "Partly Cloudy",
                "icon": "partly-cloudy-day",
                "precipIntensity": 0,
                "precipProbability": 0,
                "temperature": 67.28,
                "apparentTemperature": 67.28,
                "dewPoint": 37.1,
                "humidity": 0.33,
                "pressure": 1008.89,
                "windSpeed": 14.8,
                "windGust": 27.5,
                "windBearing": 252,
                "cloudCover": 0.5,
                "uvIndex": 3,
                "visibility": 6.22,
                "ozone": 383.93
            }, {
                "time": 1559577600,
                "summary": "Partly Cloudy",
                "icon": "partly-cloudy-day",
                "precipIntensity": 0,
                "precipProbability": 0,
                "temperature": 67.33,
                "apparentTemperature": 67.33,
                "dewPoint": 37.22,
                "humidity": 0.33,
                "pressure": 1008.84,
                "windSpeed": 13.89,
                "windGust": 25.69,
                "windBearing": 252,
                "cloudCover": 0.47,
                "uvIndex": 2,
                "visibility": 7.13,
                "ozone": 384.71
            }, {
                "time": 1559581200,
                "summary": "Partly Cloudy",
                "icon": "partly-cloudy-day",
                "precipIntensity": 0,
                "precipProbability": 0,
                "temperature": 66.58,
                "apparentTemperature": 66.58,
                "dewPoint": 39,
                "humidity": 0.36,
                "pressure": 1008.77,
                "windSpeed": 12.96,
                "windGust": 21.43,
                "windBearing": 251,
                "cloudCover": 0.31,
                "uvIndex": 1,
                "visibility": 10,
                "ozone": 386.09
            }, {
                "time": 1559584800,
                "summary": "Clear",
                "icon": "clear-day",
                "precipIntensity": 0,
                "precipProbability": 0,
                "temperature": 64.78,
                "apparentTemperature": 64.78,
                "dewPoint": 40.16,
                "humidity": 0.4,
                "pressure": 1008.8,
                "windSpeed": 11.76,
                "windGust": 17.88,
                "windBearing": 251,
                "cloudCover": 0.19,
                "uvIndex": 1,
                "visibility": 10,
                "ozone": 387.38
            }, {
                "time": 1559588400,
                "summary": "Clear",
                "icon": "clear-day",
                "precipIntensity": 0,
                "precipProbability": 0,
                "temperature": 62.71,
                "apparentTemperature": 62.71,
                "dewPoint": 40.07,
                "humidity": 0.43,
                "pressure": 1009.07,
                "windSpeed": 10.09,
                "windGust": 15.67,
                "windBearing": 250,
                "cloudCover": 0.12,
                "uvIndex": 0,
                "visibility": 10,
                "ozone": 388.71
            }, {
                "time": 1559592000,
                "summary": "Clear",
                "icon": "clear-day",
                "precipIntensity": 0,
                "precipProbability": 0,
                "temperature": 60,
                "apparentTemperature": 60,
                "dewPoint": 39.99,
                "humidity": 0.48,
                "pressure": 1009.47,
                "windSpeed": 8.32,
                "windGust": 13.27,
                "windBearing": 248,
                "cloudCover": 0.05,
                "uvIndex": 0,
                "visibility": 10,
                "ozone": 389.96
            }, {
                "time": 1559595600,
                "summary": "Clear",
                "icon": "clear-night",
                "precipIntensity": 0,
                "precipProbability": 0,
                "temperature": 57.86,
                "apparentTemperature": 57.86,
                "dewPoint": 39.93,
                "humidity": 0.51,
                "pressure": 1009.75,
                "windSpeed": 6.91,
                "windGust": 11.45,
                "windBearing": 244,
                "cloudCover": 0,
                "uvIndex": 0,
                "visibility": 10,
                "ozone": 390.4
            }, {
                "time": 1559599200,
                "summary": "Clear",
                "icon": "clear-night",
                "precipIntensity": 0,
                "precipProbability": 0,
                "temperature": 56.3,
                "apparentTemperature": 56.3,
                "dewPoint": 40.05,
                "humidity": 0.54,
                "pressure": 1009.83,
                "windSpeed": 6.13,
                "windGust": 10.66,
                "windBearing": 240,
                "cloudCover": 0,
                "uvIndex": 0,
                "visibility": 10,
                "ozone": 389.47
            }, {
                "time": 1559602800,
                "summary": "Clear",
                "icon": "clear-night",
                "precipIntensity": 0,
                "precipProbability": 0,
                "temperature": 54.99,
                "apparentTemperature": 54.99,
                "dewPoint": 40.26,
                "humidity": 0.57,
                "pressure": 1009.8,
                "windSpeed": 5.7,
                "windGust": 10.32,
                "windBearing": 235,
                "cloudCover": 0,
                "uvIndex": 0,
                "visibility": 10,
                "ozone": 387.77
            }, {
                "time": 1559606400,
                "summary": "Clear",
                "icon": "clear-night",
                "precipIntensity": 0,
                "precipProbability": 0,
                "temperature": 53.8,
                "apparentTemperature": 53.8,
                "dewPoint": 40.58,
                "humidity": 0.61,
                "pressure": 1009.69,
                "windSpeed": 5.38,
                "windGust": 10.13,
                "windBearing": 228,
                "cloudCover": 0.01,
                "uvIndex": 0,
                "visibility": 10,
                "ozone": 386.14
            }, {
                "time": 1559610000,
                "summary": "Clear",
                "icon": "clear-night",
                "precipIntensity": 0,
                "precipProbability": 0,
                "temperature": 52.56,
                "apparentTemperature": 52.56,
                "dewPoint": 41.09,
                "humidity": 0.65,
                "pressure": 1009.48,
                "windSpeed": 5.1,
                "windGust": 9.76,
                "windBearing": 219,
                "cloudCover": 0.01,
                "uvIndex": 0,
                "visibility": 10,
                "ozone": 385.07
            }, {
                "time": 1559613600,
                "summary": "Clear",
                "icon": "clear-night",
                "precipIntensity": 0,
                "precipProbability": 0,
                "temperature": 51.38,
                "apparentTemperature": 51.38,
                "dewPoint": 41.77,
                "humidity": 0.7,
                "pressure": 1009.2,
                "windSpeed": 4.94,
                "windGust": 9.46,
                "windBearing": 208,
                "cloudCover": 0.02,
                "uvIndex": 0,
                "visibility": 10,
                "ozone": 384.16
            }, {
                "time": 1559617200,
                "summary": "Clear",
                "icon": "clear-night",
                "precipIntensity": 0,
                "precipProbability": 0,
                "temperature": 50.87,
                "apparentTemperature": 50.87,
                "dewPoint": 42.38,
                "humidity": 0.73,
                "pressure": 1008.95,
                "windSpeed": 4.9,
                "windGust": 9.48,
                "windBearing": 199,
                "cloudCover": 0.03,
                "uvIndex": 0,
                "visibility": 10,
                "ozone": 383.38
            }, {
                "time": 1559620800,
                "summary": "Clear",
                "icon": "clear-day",
                "precipIntensity": 0,
                "precipProbability": 0,
                "temperature": 51.26,
                "apparentTemperature": 51.26,
                "dewPoint": 42.82,
                "humidity": 0.73,
                "pressure": 1008.8,
                "windSpeed": 5,
                "windGust": 10.11,
                "windBearing": 195,
                "cloudCover": 0.12,
                "uvIndex": 0,
                "visibility": 10,
                "ozone": 382.96
            }, {
                "time": 1559624400,
                "summary": "Partly Cloudy",
                "icon": "partly-cloudy-day",
                "precipIntensity": 0,
                "precipProbability": 0,
                "temperature": 51.32,
                "apparentTemperature": 51.32,
                "dewPoint": 43.23,
                "humidity": 0.74,
                "pressure": 1008.67,
                "windSpeed": 5.22,
                "windGust": 11.06,
                "windBearing": 191,
                "cloudCover": 0.25,
                "uvIndex": 0,
                "visibility": 10,
                "ozone": 382.61
            }, {
                "time": 1559628000,
                "summary": "Partly Cloudy",
                "icon": "partly-cloudy-day",
                "precipIntensity": 0,
                "precipProbability": 0,
                "temperature": 52.72,
                "apparentTemperature": 52.72,
                "dewPoint": 43.81,
                "humidity": 0.72,
                "pressure": 1008.51,
                "windSpeed": 5.6,
                "windGust": 11.78,
                "windBearing": 187,
                "cloudCover": 0.38,
                "uvIndex": 0,
                "visibility": 10,
                "ozone": 381.9
            }, {
                "time": 1559631600,
                "summary": "Partly Cloudy",
                "icon": "partly-cloudy-day",
                "precipIntensity": 0,
                "precipProbability": 0,
                "temperature": 54.16,
                "apparentTemperature": 54.16,
                "dewPoint": 44.62,
                "humidity": 0.7,
                "pressure": 1008.33,
                "windSpeed": 6.25,
                "windGust": 12.07,
                "windBearing": 180,
                "cloudCover": 0.52,
                "uvIndex": 1,
                "visibility": 10,
                "ozone": 380.26
            }, {
                "time": 1559635200,
                "summary": "Mostly Cloudy",
                "icon": "partly-cloudy-day",
                "precipIntensity": 0.0008,
                "precipProbability": 0.1,
                "precipType": "rain",
                "temperature": 56.2,
                "apparentTemperature": 56.2,
                "dewPoint": 45.57,
                "humidity": 0.67,
                "pressure": 1008.13,
                "windSpeed": 7.08,
                "windGust": 12.12,
                "windBearing": 172,
                "cloudCover": 0.66,
                "uvIndex": 2,
                "visibility": 10,
                "ozone": 378.33
            }, {
                "time": 1559638800,
                "summary": "Mostly Cloudy",
                "icon": "partly-cloudy-day",
                "precipIntensity": 0.0022,
                "precipProbability": 0.15,
                "precipType": "rain",
                "temperature": 57.74,
                "apparentTemperature": 57.74,
                "dewPoint": 46.45,
                "humidity": 0.66,
                "pressure": 1007.83,
                "windSpeed": 7.67,
                "windGust": 12.05,
                "windBearing": 166,
                "cloudCover": 0.78,
                "uvIndex": 3,
                "visibility": 10,
                "ozone": 377.54
            }, {
                "time": 1559642400,
                "summary": "Mostly Cloudy",
                "icon": "partly-cloudy-day",
                "precipIntensity": 0.0049,
                "precipProbability": 0.23,
                "precipType": "rain",
                "temperature": 58.27,
                "apparentTemperature": 58.27,
                "dewPoint": 47.14,
                "humidity": 0.66,
                "pressure": 1007.37,
                "windSpeed": 7.82,
                "windGust": 11.74,
                "windBearing": 161,
                "cloudCover": 0.83,
                "uvIndex": 3,
                "visibility": 10,
                "ozone": 379.46
            }, {
                "time": 1559646000,
                "summary": "Mostly Cloudy",
                "icon": "partly-cloudy-day",
                "precipIntensity": 0.0097,
                "precipProbability": 0.35,
                "precipType": "rain",
                "temperature": 57.82,
                "apparentTemperature": 57.82,
                "dewPoint": 47.77,
                "humidity": 0.69,
                "pressure": 1006.81,
                "windSpeed": 7.81,
                "windGust": 11.31,
                "windBearing": 160,
                "cloudCover": 0.86,
                "uvIndex": 3,
                "visibility": 10,
                "ozone": 382.45
            }, {
                "time": 1559649600,
                "summary": "Mostly Cloudy",
                "icon": "partly-cloudy-day",
                "precipIntensity": 0.0155,
                "precipProbability": 0.51,
                "precipType": "rain",
                "temperature": 57.13,
                "apparentTemperature": 57.13,
                "dewPoint": 48.31,
                "humidity": 0.72,
                "pressure": 1006.26,
                "windSpeed": 7.86,
                "windGust": 11.14,
                "windBearing": 157,
                "cloudCover": 0.89,
                "uvIndex": 3,
                "visibility": 9.04,
                "ozone": 383.69
            }, {
                "time": 1559653200,
                "summary": "Mostly Cloudy",
                "icon": "partly-cloudy-day",
                "precipIntensity": 0.0211,
                "precipProbability": 0.62,
                "precipType": "rain",
                "temperature": 56.98,
                "apparentTemperature": 56.98,
                "dewPoint": 48.62,
                "humidity": 0.74,
                "pressure": 1005.73,
                "windSpeed": 8.06,
                "windGust": 11.59,
                "windBearing": 151,
                "cloudCover": 0.93,
                "uvIndex": 3,
                "visibility": 7.36,
                "ozone": 380.91
            }, {
                "time": 1559656800,
                "summary": "Light Rain",
                "icon": "rain",
                "precipIntensity": 0.027,
                "precipProbability": 0.66,
                "precipType": "rain",
                "temperature": 57.05,
                "apparentTemperature": 57.05,
                "dewPoint": 48.77,
                "humidity": 0.74,
                "pressure": 1005.21,
                "windSpeed": 8.24,
                "windGust": 12.32,
                "windBearing": 145,
                "cloudCover": 0.98,
                "uvIndex": 3,
                "visibility": 5.76,
                "ozone": 376.34
            }, {
                "time": 1559660400,
                "summary": "Light Rain",
                "icon": "rain",
                "precipIntensity": 0.0305,
                "precipProbability": 0.66,
                "precipType": "rain",
                "temperature": 57.15,
                "apparentTemperature": 57.15,
                "dewPoint": 48.95,
                "humidity": 0.74,
                "pressure": 1004.7,
                "windSpeed": 8.24,
                "windGust": 12.72,
                "windBearing": 139,
                "cloudCover": 1,
                "uvIndex": 2,
                "visibility": 4.73,
                "ozone": 374.29
            }, {
                "time": 1559664000,
                "summary": "Light Rain",
                "icon": "rain",
                "precipIntensity": 0.0294,
                "precipProbability": 0.63,
                "precipType": "rain",
                "temperature": 57.56,
                "apparentTemperature": 57.56,
                "dewPoint": 49.43,
                "humidity": 0.74,
                "pressure": 1004.2,
                "windSpeed": 8.13,
                "windGust": 12.65,
                "windBearing": 132,
                "cloudCover": 0.98,
                "uvIndex": 2,
                "visibility": 4.38,
                "ozone": 377.8
            }, {
                "time": 1559667600,
                "summary": "Overcast",
                "icon": "cloudy",
                "precipIntensity": 0.0265,
                "precipProbability": 0.58,
                "precipType": "rain",
                "temperature": 57.89,
                "apparentTemperature": 57.89,
                "dewPoint": 49.99,
                "humidity": 0.75,
                "pressure": 1003.72,
                "windSpeed": 7.92,
                "windGust": 12.26,
                "windBearing": 122,
                "cloudCover": 0.94,
                "uvIndex": 1,
                "visibility": 4.6,
                "ozone": 383.75
            }, {
                "time": 1559671200,
                "summary": "Mostly Cloudy",
                "icon": "partly-cloudy-day",
                "precipIntensity": 0.0218,
                "precipProbability": 0.51,
                "precipType": "rain",
                "temperature": 58.12,
                "apparentTemperature": 58.12,
                "dewPoint": 50.29,
                "humidity": 0.75,
                "pressure": 1003.38,
                "windSpeed": 7.44,
                "windGust": 11.32,
                "windBearing": 115,
                "cloudCover": 0.88,
                "uvIndex": 1,
                "visibility": 5.67,
                "ozone": 387.86
            }, {
                "time": 1559674800,
                "summary": "Mostly Cloudy",
                "icon": "partly-cloudy-day",
                "precipIntensity": 0.0117,
                "precipProbability": 0.42,
                "precipType": "rain",
                "temperature": 57.52,
                "apparentTemperature": 57.52,
                "dewPoint": 50.11,
                "humidity": 0.76,
                "pressure": 1003.28,
                "windSpeed": 6.32,
                "windGust": 9.28,
                "windBearing": 118,
                "cloudCover": 0.76,
                "uvIndex": 0,
                "visibility": 8.45,
                "ozone": 387.94
            }, {
                "time": 1559678400,
                "summary": "Partly Cloudy",
                "icon": "partly-cloudy-day",
                "precipIntensity": 0.0032,
                "precipProbability": 0.31,
                "precipType": "rain",
                "temperature": 56.56,
                "apparentTemperature": 56.56,
                "dewPoint": 49.56,
                "humidity": 0.77,
                "pressure": 1003.33,
                "windSpeed": 4.96,
                "windGust": 6.68,
                "windBearing": 124,
                "cloudCover": 0.59,
                "uvIndex": 0,
                "visibility": 10,
                "ozone": 386.13
            }, {
                "time": 1559682000,
                "summary": "Partly Cloudy",
                "icon": "partly-cloudy-night",
                "precipIntensity": 0.0006,
                "precipProbability": 0.23,
                "precipType": "rain",
                "temperature": 55.55,
                "apparentTemperature": 55.55,
                "dewPoint": 49.02,
                "humidity": 0.79,
                "pressure": 1003.35,
                "windSpeed": 4.13,
                "windGust": 5.11,
                "windBearing": 131,
                "cloudCover": 0.49,
                "uvIndex": 0,
                "visibility": 10,
                "ozone": 385.08
            }, {
                "time": 1559685600,
                "summary": "Partly Cloudy",
                "icon": "partly-cloudy-night",
                "precipIntensity": 0.0014,
                "precipProbability": 0.25,
                "precipType": "rain",
                "temperature": 54.69,
                "apparentTemperature": 54.69,
                "dewPoint": 48.84,
                "humidity": 0.81,
                "pressure": 1003.25,
                "windSpeed": 4.26,
                "windGust": 5.48,
                "windBearing": 137,
                "cloudCover": 0.49,
                "uvIndex": 0,
                "visibility": 10,
                "ozone": 386.04
            }, {
                "time": 1559689200,
                "summary": "Partly Cloudy",
                "icon": "partly-cloudy-night",
                "precipIntensity": 0.0057,
                "precipProbability": 0.18,
                "precipType": "rain",
                "temperature": 54.03,
                "apparentTemperature": 54.03,
                "dewPoint": 48.83,
                "humidity": 0.83,
                "pressure": 1003.11,
                "windSpeed": 4.82,
                "windGust": 6.73,
                "windBearing": 147,
                "cloudCover": 0.56,
                "uvIndex": 0,
                "visibility": 10,
                "ozone": 387.6
            }, {
                "time": 1559692800,
                "summary": "Partly Cloudy",
                "icon": "partly-cloudy-night",
                "precipIntensity": 0.0096,
                "precipProbability": 0.14,
                "precipType": "rain",
                "temperature": 53.52,
                "apparentTemperature": 53.52,
                "dewPoint": 48.81,
                "humidity": 0.84,
                "pressure": 1003,
                "windSpeed": 5.16,
                "windGust": 8.02,
                "windBearing": 160,
                "cloudCover": 0.59,
                "uvIndex": 0,
                "visibility": 8.84,
                "ozone": 388.52
            }, {
                "time": 1559696400,
                "summary": "Partly Cloudy",
                "icon": "partly-cloudy-night",
                "precipIntensity": 0.0071,
                "precipProbability": 0.1,
                "precipType": "rain",
                "temperature": 53.04,
                "apparentTemperature": 53.04,
                "dewPoint": 48.64,
                "humidity": 0.85,
                "pressure": 1002.91,
                "windSpeed": 5.11,
                "windGust": 9.24,
                "windBearing": 176,
                "cloudCover": 0.54,
                "uvIndex": 0,
                "visibility": 8.21,
                "ozone": 388.09
            }, {
                "time": 1559700000,
                "summary": "Partly Cloudy",
                "icon": "partly-cloudy-night",
                "precipIntensity": 0.0033,
                "precipProbability": 0.08,
                "precipType": "rain",
                "temperature": 52.3,
                "apparentTemperature": 52.3,
                "dewPoint": 48.31,
                "humidity": 0.86,
                "pressure": 1002.85,
                "windSpeed": 5.02,
                "windGust": 10.5,
                "windBearing": 195,
                "cloudCover": 0.44,
                "uvIndex": 0,
                "visibility": 8.17,
                "ozone": 386.91
            }, {
                "time": 1559703600,
                "summary": "Partly Cloudy",
                "icon": "partly-cloudy-night",
                "precipIntensity": 0.0019,
                "precipProbability": 0.06,
                "precipType": "rain",
                "temperature": 51.81,
                "apparentTemperature": 51.81,
                "dewPoint": 48.07,
                "humidity": 0.87,
                "pressure": 1002.88,
                "windSpeed": 4.99,
                "windGust": 11.19,
                "windBearing": 206,
                "cloudCover": 0.37,
                "uvIndex": 0,
                "visibility": 8.78,
                "ozone": 385.45
            }, {
                "time": 1559707200,
                "summary": "Partly Cloudy",
                "icon": "partly-cloudy-day",
                "precipIntensity": 0.0019,
                "precipProbability": 0.07,
                "precipType": "rain",
                "temperature": 51.75,
                "apparentTemperature": 51.75,
                "dewPoint": 48.27,
                "humidity": 0.88,
                "pressure": 1003.1,
                "windSpeed": 5.03,
                "windGust": 10.62,
                "windBearing": 203,
                "cloudCover": 0.32,
                "uvIndex": 0,
                "visibility": 10,
                "ozone": 383.57
            }, {
                "time": 1559710800,
                "summary": "Partly Cloudy",
                "icon": "partly-cloudy-day",
                "precipIntensity": 0.0026,
                "precipProbability": 0.08,
                "precipType": "rain",
                "temperature": 52.12,
                "apparentTemperature": 52.12,
                "dewPoint": 48.73,
                "humidity": 0.88,
                "pressure": 1003.43,
                "windSpeed": 5.08,
                "windGust": 9.4,
                "windBearing": 193,
                "cloudCover": 0.29,
                "uvIndex": 0,
                "visibility": 10,
                "ozone": 381.25
            }, {
                "time": 1559714400,
                "summary": "Partly Cloudy",
                "icon": "partly-cloudy-day",
                "precipIntensity": 0.0028,
                "precipProbability": 0.08,
                "precipType": "rain",
                "temperature": 53.28,
                "apparentTemperature": 53.28,
                "dewPoint": 49.09,
                "humidity": 0.86,
                "pressure": 1003.67,
                "windSpeed": 5.1,
                "windGust": 8.45,
                "windBearing": 188,
                "cloudCover": 0.34,
                "uvIndex": 0,
                "visibility": 10,
                "ozone": 378.93
            }, {
                "time": 1559718000,
                "summary": "Partly Cloudy",
                "icon": "partly-cloudy-day",
                "precipIntensity": 0.0016,
                "precipProbability": 0.05,
                "precipType": "rain",
                "temperature": 54.75,
                "apparentTemperature": 54.75,
                "dewPoint": 49.18,
                "humidity": 0.81,
                "pressure": 1003.65,
                "windSpeed": 4.91,
                "windGust": 8.17,
                "windBearing": 196,
                "cloudCover": 0.54,
                "uvIndex": 1,
                "visibility": 10,
                "ozone": 376.71
            }, {
                "time": 1559721600,
                "summary": "Mostly Cloudy",
                "icon": "partly-cloudy-day",
                "precipIntensity": 0.0004,
                "precipProbability": 0.02,
                "precipType": "rain",
                "temperature": 56.75,
                "apparentTemperature": 56.75,
                "dewPoint": 49.16,
                "humidity": 0.76,
                "pressure": 1003.54,
                "windSpeed": 4.6,
                "windGust": 8.18,
                "windBearing": 209,
                "cloudCover": 0.81,
                "uvIndex": 2,
                "visibility": 10,
                "ozone": 374.41
            }, {
                "time": 1559725200,
                "summary": "Overcast",
                "icon": "cloudy",
                "precipIntensity": 0,
                "precipProbability": 0,
                "temperature": 58.79,
                "apparentTemperature": 58.79,
                "dewPoint": 49.08,
                "humidity": 0.7,
                "pressure": 1003.51,
                "windSpeed": 4.49,
                "windGust": 8.35,
                "windBearing": 215,
                "cloudCover": 1,
                "uvIndex": 2,
                "visibility": 10,
                "ozone": 372.08
            }, {
                "time": 1559728800,
                "summary": "Overcast",
                "icon": "cloudy",
                "precipIntensity": 0,
                "precipProbability": 0,
                "temperature": 60.52,
                "apparentTemperature": 60.52,
                "dewPoint": 48.88,
                "humidity": 0.65,
                "pressure": 1003.7,
                "windSpeed": 4.89,
                "windGust": 8.77,
                "windBearing": 204,
                "cloudCover": 1,
                "uvIndex": 3,
                "visibility": 10,
                "ozone": 369.48
            }, {
                "time": 1559732400,
                "summary": "Overcast",
                "icon": "cloudy",
                "precipIntensity": 0,
                "precipProbability": 0,
                "temperature": 61.83,
                "apparentTemperature": 61.83,
                "dewPoint": 48.57,
                "humidity": 0.62,
                "pressure": 1003.97,
                "windSpeed": 5.53,
                "windGust": 9.33,
                "windBearing": 186,
                "cloudCover": 0.96,
                "uvIndex": 3,
                "visibility": 10,
                "ozone": 366.86
            }, {
                "time": 1559736000,
                "summary": "Mostly Cloudy",
                "icon": "partly-cloudy-day",
                "precipIntensity": 0,
                "precipProbability": 0,
                "temperature": 62.92,
                "apparentTemperature": 62.92,
                "dewPoint": 48.37,
                "humidity": 0.59,
                "pressure": 1004.14,
                "windSpeed": 5.95,
                "windGust": 9.6,
                "windBearing": 179,
                "cloudCover": 0.92,
                "uvIndex": 4,
                "visibility": 10,
                "ozone": 364.8
            }, {
                "time": 1559739600,
                "summary": "Mostly Cloudy",
                "icon": "partly-cloudy-day",
                "precipIntensity": 0.0002,
                "precipProbability": 0.03,
                "precipType": "rain",
                "temperature": 63.64,
                "apparentTemperature": 63.64,
                "dewPoint": 48.35,
                "humidity": 0.57,
                "pressure": 1004.11,
                "windSpeed": 5.8,
                "windGust": 9.31,
                "windBearing": 196,
                "cloudCover": 0.93,
                "uvIndex": 3,
                "visibility": 10,
                "ozone": 363.46
            }, {
                "time": 1559743200,
                "summary": "Overcast",
                "icon": "cloudy",
                "precipIntensity": 0.0006,
                "precipProbability": 0.03,
                "precipType": "rain",
                "temperature": 63.82,
                "apparentTemperature": 63.82,
                "dewPoint": 48.46,
                "humidity": 0.57,
                "pressure": 1003.99,
                "windSpeed": 5.44,
                "windGust": 8.7,
                "windBearing": 221,
                "cloudCover": 0.97,
                "uvIndex": 3,
                "visibility": 10,
                "ozone": 362.72
            }]
        },
        "daily": {
            "summary": "Light rain tomorrow through next Monday, with high temperatures falling to 58°F tomorrow.",
            "icon": "rain",
            "data": [{
                "time": 1559516400,
                "summary": "Partly cloudy until evening and breezy in the morning.",
                "icon": "wind",
                "sunriseTime": 1559533321,
                "sunsetTime": 1559593778,
                "moonPhase": 0.99,
                "precipIntensity": 0.0001,
                "precipIntensityMax": 0.0002,
                "precipIntensityMaxTime": 1559530800,
                "precipProbability": 0.03,
                "precipType": "rain",
                "temperatureHigh": 67.33,
                "temperatureHighTime": 1559577600,
                "temperatureLow": 50.87,
                "temperatureLowTime": 1559617200,
                "apparentTemperatureHigh": 67.33,
                "apparentTemperatureHighTime": 1559577600,
                "apparentTemperatureLow": 50.87,
                "apparentTemperatureLowTime": 1559617200,
                "dewPoint": 41.35,
                "humidity": 0.5,
                "pressure": 1008.03,
                "windSpeed": 13.22,
                "windGust": 31.78,
                "windGustTime": 1559548800,
                "windBearing": 245,
                "cloudCover": 0.4,
                "uvIndex": 5,
                "uvIndexTime": 1559563200,
                "visibility": 7.2,
                "ozone": 385.5,
                "temperatureMin": 54.71,
                "temperatureMinTime": 1559538000,
                "temperatureMax": 67.33,
                "temperatureMaxTime": 1559577600,
                "apparentTemperatureMin": 54.71,
                "apparentTemperatureMinTime": 1559538000,
                "apparentTemperatureMax": 67.33,
                "apparentTemperatureMaxTime": 1559577600
            }, {
                "time": 1559602800,
                "summary": "Light rain starting in the afternoon, continuing until evening.",
                "icon": "rain",
                "sunriseTime": 1559619674,
                "sunsetTime": 1559680245,
                "moonPhase": 0.03,
                "precipIntensity": 0.0086,
                "precipIntensityMax": 0.0305,
                "precipIntensityMaxTime": 1559660400,
                "precipProbability": 0.87,
                "precipType": "rain",
                "temperatureHigh": 58.27,
                "temperatureHighTime": 1559642400,
                "temperatureLow": 51.75,
                "temperatureLowTime": 1559707200,
                "apparentTemperatureHigh": 58.27,
                "apparentTemperatureHighTime": 1559642400,
                "apparentTemperatureLow": 51.75,
                "apparentTemperatureLowTime": 1559707200,
                "dewPoint": 46.22,
                "humidity": 0.71,
                "pressure": 1006.58,
                "windSpeed": 5.38,
                "windGust": 12.72,
                "windGustTime": 1559660400,
                "windBearing": 161,
                "cloudCover": 0.56,
                "uvIndex": 3,
                "uvIndexTime": 1559638800,
                "visibility": 8.75,
                "ozone": 382.58,
                "temperatureMin": 50.87,
                "temperatureMinTime": 1559617200,
                "temperatureMax": 58.27,
                "temperatureMaxTime": 1559642400,
                "apparentTemperatureMin": 50.87,
                "apparentTemperatureMinTime": 1559617200,
                "apparentTemperatureMax": 58.27,
                "apparentTemperatureMaxTime": 1559642400
            }, {
                "time": 1559689200,
                "summary": "Rain overnight.",
                "icon": "rain",
                "sunriseTime": 1559706029,
                "sunsetTime": 1559766710,
                "moonPhase": 0.07,
                "precipIntensity": 0.0036,
                "precipIntensityMax": 0.0268,
                "precipIntensityMaxTime": 1559772000,
                "precipProbability": 0.42,
                "precipType": "rain",
                "temperatureHigh": 63.82,
                "temperatureHighTime": 1559743200,
                "temperatureLow": 51.02,
                "temperatureLowTime": 1559790000,
                "apparentTemperatureHigh": 63.82,
                "apparentTemperatureHighTime": 1559743200,
                "apparentTemperatureLow": 51.02,
                "apparentTemperatureLowTime": 1559790000,
                "dewPoint": 48.54,
                "humidity": 0.73,
                "pressure": 1003.78,
                "windSpeed": 3.22,
                "windGust": 12.73,
                "windGustTime": 1559772000,
                "windBearing": 199,
                "cloudCover": 0.77,
                "uvIndex": 4,
                "uvIndexTime": 1559736000,
                "visibility": 9.75,
                "ozone": 373.9,
                "temperatureMin": 51.75,
                "temperatureMinTime": 1559707200,
                "temperatureMax": 63.82,
                "temperatureMaxTime": 1559743200,
                "apparentTemperatureMin": 51.75,
                "apparentTemperatureMinTime": 1559707200,
                "apparentTemperatureMax": 63.82,
                "apparentTemperatureMaxTime": 1559743200
            }, {
                "time": 1559775600,
                "summary": "Partly cloudy starting in the evening.",
                "icon": "partly-cloudy-night",
                "sunriseTime": 1559792388,
                "sunsetTime": 1559853172,
                "moonPhase": 0.11,
                "precipIntensity": 0.0118,
                "precipIntensityMax": 0.0713,
                "precipIntensityMaxTime": 1559779200,
                "precipProbability": 0.67,
                "precipType": "rain",
                "temperatureHigh": 63.1,
                "temperatureHighTime": 1559833200,
                "temperatureLow": 48.32,
                "temperatureLowTime": 1559876400,
                "apparentTemperatureHigh": 63.1,
                "apparentTemperatureHighTime": 1559833200,
                "apparentTemperatureLow": 44.61,
                "apparentTemperatureLowTime": 1559876400,
                "dewPoint": 44.74,
                "humidity": 0.66,
                "pressure": 1006.75,
                "windSpeed": 8.07,
                "windGust": 14.81,
                "windGustTime": 1559782800,
                "windBearing": 221,
                "cloudCover": 0.46,
                "uvIndex": 6,
                "uvIndexTime": 1559818800,
                "visibility": 10,
                "ozone": 384.15,
                "temperatureMin": 51.02,
                "temperatureMinTime": 1559790000,
                "temperatureMax": 63.1,
                "temperatureMaxTime": 1559833200,
                "apparentTemperatureMin": 51.02,
                "apparentTemperatureMinTime": 1559790000,
                "apparentTemperatureMax": 63.1,
                "apparentTemperatureMaxTime": 1559833200
            }, {
                "time": 1559862000,
                "summary": "Overcast throughout the day.",
                "icon": "cloudy",
                "sunriseTime": 1559878750,
                "sunsetTime": 1559939631,
                "moonPhase": 0.14,
                "precipIntensity": 0.0069,
                "precipIntensityMax": 0.0188,
                "precipIntensityMaxTime": 1559926800,
                "precipProbability": 0.93,
                "precipType": "rain",
                "temperatureHigh": 61.08,
                "temperatureHighTime": 1559923200,
                "temperatureLow": 51.23,
                "temperatureLowTime": 1559966400,
                "apparentTemperatureHigh": 61.08,
                "apparentTemperatureHighTime": 1559923200,
                "apparentTemperatureLow": 51.23,
                "apparentTemperatureLowTime": 1559966400,
                "dewPoint": 45.39,
                "humidity": 0.68,
                "pressure": 1009.84,
                "windSpeed": 3.29,
                "windGust": 30.62,
                "windGustTime": 1559919600,
                "windBearing": 145,
                "cloudCover": 0.71,
                "uvIndex": 3,
                "uvIndexTime": 1559898000,
                "visibility": 7.89,
                "ozone": 381.81,
                "temperatureMin": 48.32,
                "temperatureMinTime": 1559876400,
                "temperatureMax": 61.08,
                "temperatureMaxTime": 1559923200,
                "apparentTemperatureMin": 44.61,
                "apparentTemperatureMinTime": 1559876400,
                "apparentTemperatureMax": 61.08,
                "apparentTemperatureMaxTime": 1559923200
            }, {
                "time": 1559948400,
                "summary": "Breezy and mostly cloudy until afternoon.",
                "icon": "wind",
                "sunriseTime": 1559965116,
                "sunsetTime": 1560026087,
                "moonPhase": 0.18,
                "precipIntensity": 0.0045,
                "precipIntensityMax": 0.0161,
                "precipIntensityMaxTime": 1559973600,
                "precipProbability": 0.78,
                "precipType": "rain",
                "temperatureHigh": 62.14,
                "temperatureHighTime": 1560009600,
                "temperatureLow": 48.29,
                "temperatureLowTime": 1560049200,
                "apparentTemperatureHigh": 62.14,
                "apparentTemperatureHighTime": 1560009600,
                "apparentTemperatureLow": 43.89,
                "apparentTemperatureLowTime": 1560049200,
                "dewPoint": 43.52,
                "humidity": 0.64,
                "pressure": 1008.77,
                "windSpeed": 12.3,
                "windGust": 28.21,
                "windGustTime": 1559991600,
                "windBearing": 270,
                "cloudCover": 0.61,
                "uvIndex": 4,
                "uvIndexTime": 1559998800,
                "visibility": 8.69,
                "ozone": 399.43,
                "temperatureMin": 51.23,
                "temperatureMinTime": 1559966400,
                "temperatureMax": 62.14,
                "temperatureMaxTime": 1560009600,
                "apparentTemperatureMin": 51.23,
                "apparentTemperatureMinTime": 1559966400,
                "apparentTemperatureMax": 62.14,
                "apparentTemperatureMaxTime": 1560009600
            }, {
                "time": 1560034800,
                "summary": "Mostly cloudy throughout the day.",
                "icon": "partly-cloudy-day",
                "sunriseTime": 1560051485,
                "sunsetTime": 1560112540,
                "moonPhase": 0.22,
                "precipIntensity": 0.0041,
                "precipIntensityMax": 0.0122,
                "precipIntensityMaxTime": 1560114000,
                "precipProbability": 0.81,
                "precipType": "rain",
                "temperatureHigh": 61.26,
                "temperatureHighTime": 1560085200,
                "temperatureLow": 50.8,
                "temperatureLowTime": 1560139200,
                "apparentTemperatureHigh": 61.26,
                "apparentTemperatureHighTime": 1560085200,
                "apparentTemperatureLow": 50.8,
                "apparentTemperatureLowTime": 1560139200,
                "dewPoint": 44.47,
                "humidity": 0.67,
                "pressure": 1016.77,
                "windSpeed": 9.67,
                "windGust": 22.7,
                "windGustTime": 1560038400,
                "windBearing": 185,
                "cloudCover": 0.57,
                "uvIndex": 4,
                "uvIndexTime": 1560078000,
                "visibility": 9.39,
                "ozone": 386.85,
                "temperatureMin": 48.29,
                "temperatureMinTime": 1560049200,
                "temperatureMax": 61.26,
                "temperatureMaxTime": 1560085200,
                "apparentTemperatureMin": 43.89,
                "apparentTemperatureMinTime": 1560049200,
                "apparentTemperatureMax": 61.26,
                "apparentTemperatureMaxTime": 1560085200
            }, {
                "time": 1560121200,
                "summary": "Rain in the morning.",
                "icon": "rain",
                "sunriseTime": 1560137857,
                "sunsetTime": 1560198991,
                "moonPhase": 0.26,
                "precipIntensity": 0.0217,
                "precipIntensityMax": 0.0629,
                "precipIntensityMaxTime": 1560157200,
                "precipProbability": 0.96,
                "precipType": "rain",
                "temperatureHigh": 64.65,
                "temperatureHighTime": 1560178800,
                "temperatureLow": 50.58,
                "temperatureLowTime": 1560222000,
                "apparentTemperatureHigh": 64.65,
                "apparentTemperatureHighTime": 1560178800,
                "apparentTemperatureLow": 50.58,
                "apparentTemperatureLowTime": 1560222000,
                "dewPoint": 48.52,
                "humidity": 0.74,
                "pressure": 1015.25,
                "windSpeed": 4.25,
                "windGust": 18.94,
                "windGustTime": 1560124800,
                "windBearing": 110,
                "cloudCover": 0.81,
                "uvIndex": 3,
                "uvIndexTime": 1560160800,
                "visibility": 4.57,
                "ozone": 382.05,
                "temperatureMin": 50.8,
                "temperatureMinTime": 1560139200,
                "temperatureMax": 64.65,
                "temperatureMaxTime": 1560178800,
                "apparentTemperatureMin": 50.8,
                "apparentTemperatureMinTime": 1560139200,
                "apparentTemperatureMax": 64.65,
                "apparentTemperatureMaxTime": 1560178800
            }]
        },
        "flags": {
            "sources": ["nearest-precip", "meteoalarm", "cmc", "gfs", "icon", "isd", "madis", "darksky"],
            "meteoalarm-license": "Based on data from EUMETNET - MeteoAlarm [https://www.meteoalarm.eu/]. Time delays between this website and the MeteoAlarm website are possible; for the most up to date information about alert levels as published by the participating National Meteorological Services please use the MeteoAlarm website.",
            "nearest-station": 0.039,
            "units": "us"
        },
        "offset": 1
    },
    "headers": {
        "date": "Mon, 03 Jun 2019 14:43:39 GMT",
        "content-type": "application/json; charset=utf-8",
        "content-length": "29620",
        "connection": "close",
        "x-authentication-time": "1ms",
        "cache-control": "max-age=60",
        "expires": "Mon, 03 Jun 2019 14:44:39 +0000",
        "x-forecast-api-calls": "91",
        "x-content-type-options": "nosniff",
        "x-response-time": "97.582ms",
        "vary": "Accept-Encoding"
    },
    "request": {
        "uri": {
            "protocol": "https:",
            "slashes": true,
            "auth": null,
            "host": "api.darksky.net",
            "port": 443,
            "hostname": "api.darksky.net",
            "hash": null,
            "search": null,
            "query": null,
            "pathname": "/forecast/a8a04b61d470fc7b043defebbec8409c/53.79972,-1.54917",
            "path": "/forecast/a8a04b61d470fc7b043defebbec8409c/53.79972,-1.54917",
            "href": "https://api.darksky.net/forecast/a8a04b61d470fc7b043defebbec8409c/53.79972,-1.54917"
        },
        "method": "GET",
        "headers": {
            "accept": "application/json"
        }
    }
}